epson_connect/__init__.py
epson_connect/authenticate.py
epson_connect/client.py
epson_connect/printer.py
epson_connect/printer_settings.py
epson_connect/scanner.py
epson_connect-0.2.3.dist-info/LICENSE
epson_connect-0.2.3.dist-info/METADATA
epson_connect-0.2.3.dist-info/WHEEL
epson_connect-0.2.3.dist-info/RECORD
