Metadata-Version: 2.1
Name: epson-connect
Version: 0.2.3
Summary: Bindings for the Espon Connect API
Home-page: https://pypi.org/project/epson-connect/
License: MIT
Keywords: epson,connect,api
Author: Paul Logston
Author-email: paul.logston@gmail.com
Maintainer: Paul Logston
Maintainer-email: paul.logston@gmail.com
Requires-Python: >=3.9
Classifier: Development Status :: 4 - Beta
Classifier: Environment :: Web Environment
Classifier: Intended Audience :: Developers
Classifier: License :: OSI Approved :: MIT License
Classifier: Natural Language :: English
Classifier: Operating System :: OS Independent
Classifier: Programming Language :: Python :: 3
Classifier: Programming Language :: Python :: 3.9
Classifier: Programming Language :: Python :: 3.10
Classifier: Programming Language :: Python :: 3.11
Classifier: Topic :: Internet
Classifier: Topic :: Printing
Classifier: Topic :: Software Development :: Libraries
Requires-Dist: requests (>=2.31.0,<3.0.0)
Project-URL: Repository, https://github.com/logston/epson-connect
